[
       {
              "ingredient": "garlic",
              "state": [
                     {
                            "physical_state": "peeled",
                            "location": []
                     },
                     {
                            "physical_state": "peeled",
                            "location": "cutting board"
                     },
                     {
                            "physical_state": "chopped",
                            "location": "cutting board"
                     },
                     {
                            "physical_state": "chopped",
                            "location": "spoon"
                     }
              ],
              "motion": [
                     "pick-and-place",
                     "chop",
                     "scoop",
                     "spread"
              ],
              "end_product": "rib"
       },
       {
              "ingredient": "lemon",
              "state": [
                     {
                            "physical_state": "whole",
                            "location": []
                     },
                     {
                            "physical_state": "whole",
                            "location": "cutting board"
                     },
                     {
                            "physical_state": "sliced",
                            "location": "surface"
                     }
              ],
              "motion": [
                     "pick-and-place",
                     "slice",
                     "pick-and-place"
              ],
              "end_product": "rib"
       },
       {
              "ingredient": "aluminium foil",
              "state": [
                     {
                            "physical_state": "",
                            "location": "box"
                     }
              ],
              "motion": [
                     "tear"
              ],
              "end_product": null
       },
       {
              "ingredient": "rib",
              "state": [
                     {
                            "physical_state": "raw",
                            "location": "packet"
                     },
                     {
                            "physical_state": "raw",
                            "location": "baking tray"
                     },
                     {
                            "physical_state": "barbecued",
                            "location": "baking tray"
                     }
              ],
              "motion": [
                     "pick-and-place",
                     "sprinkle",
                     "pick-and-place"
              ],
              "end_product": null
       },
       {
              "ingredient": "salt",
              "state": [
                     {
                            "physical_state": "granulated",
                            "location": []
                     }
              ],
              "motion": [
                     "sprinkle"
              ],
              "end_product": "rib"
       },
       {
              "ingredient": "barbecue sauce",
              "state": [
                     {
                            "physical_state": "",
                            "location": "bottle"
                     }
              ],
              "motion": [
                     "pour"
              ],
              "end_product": "rib"
       }
]